{
    "m_Item1": {
        "ResponseCode": "200",
        "ResponseType": "Success",
        "Description": "Details Fetched Sucessfully"
    },
    "m_Item2": [
        {
            "DivisionCode": "1",
            "SectionName": "BAHADURPURA",
            "SECTIONCODE": "0111",
            "DivisionName": "Division 1 (CHARMINAR)",
            "TestedDate": "29-08-2023",
            "TotalNumberOfLineMans": 13,
            "TotalSupplyCycles": 54,
            "TotalCans": 175,
            "NumberofLinemanUsingNaanythaApp": 4,
            "NumberofCyclesCovered": 14,
            "NumberofCANsTested": 34
        },
        {
            "DivisionCode": "1",
            "SectionName": "CHANUDLAL BHARADARI",
            "SECTIONCODE": "0112",
            "DivisionName": "Division 1 (CHARMINAR)",
            "TestedDate": "29-08-2023",
            "TotalNumberOfLineMans": 9,
            "TotalSupplyCycles": 31,
            "TotalCans": 32,
            "NumberofLinemanUsingNaanythaApp": 3,
            "NumberofCyclesCovered": 3,
            "NumberofCANsTested": 9
        },
        {
            "DivisionCode": "1",
            "SectionName": "DARUL SHIFA",
            "SECTIONCODE": "0131",
            "DivisionName": "Division 1 (CHARMINAR)",
            "TestedDate": "29-08-2023",
            "TotalNumberOfLineMans": 8,
            "TotalSupplyCycles": 36,
            "TotalCans": 82,
            "NumberofLinemanUsingNaanythaApp": 3,
            "NumberofCyclesCovered": 8,
            "NumberofCANsTested": 16
        },
        {
            "DivisionCode": "1",
            "SectionName": "DHOOD BOWLI",
            "SECTIONCODE": "0121",
            "DivisionName": "Division 1 (CHARMINAR)",
            "TestedDate": "29-08-2023",
            "TotalNumberOfLineMans": 10,
            "TotalSupplyCycles": 51,
            "TotalCans": 37,
            "NumberofLinemanUsingNaanythaApp": 3,
            "NumberofCyclesCovered": 11,
            "NumberofCANsTested": 10
        },
        {
            "DivisionCode": "1",
            "SectionName": "HASSAN NAGAR",
            "SECTIONCODE": "0114",
            "DivisionName": "Division 1 (CHARMINAR)",
            "TestedDate": "29-08-2023",
            "TotalNumberOfLineMans": 4,
            "TotalSupplyCycles": 16,
            "TotalCans": 37,
            "NumberofLinemanUsingNaanythaApp": 3,
            "NumberofCyclesCovered": 12,
            "NumberofCANsTested": 23
        },
        {
            "DivisionCode": "1",
            "SectionName": "KISHAN BAGH",
            "SECTIONCODE": "0142",
            "DivisionName": "Division 1 (CHARMINAR)",
            "TestedDate": "29-08-2023",
            "TotalNumberOfLineMans": 7,
            "TotalSupplyCycles": 17,
            "TotalCans": 43,
            "NumberofLinemanUsingNaanythaApp": 2,
            "NumberofCyclesCovered": 3,
            "NumberofCANsTested": 6
        },
        {
            "DivisionCode": "1",
            "SectionName": "M.R.G.FILTERS",
            "SECTIONCODE": "0113",
            "DivisionName": "Division 1 (CHARMINAR)",
            "TestedDate": "29-08-2023",
            "TotalNumberOfLineMans": 4,
            "TotalSupplyCycles": 11,
            "TotalCans": 16,
            "NumberofLinemanUsingNaanythaApp": 1,
            "NumberofCyclesCovered": 1,
            "NumberofCANsTested": 1
        },
        {
            "DivisionCode": "1",
            "SectionName": "MISRIGUNJ",
            "SECTIONCODE": "0122",
            "DivisionName": "Division 1 (CHARMINAR)",
            "TestedDate": "29-08-2023",
            "TotalNumberOfLineMans": 5,
            "TotalSupplyCycles": 25,
            "TotalCans": 21,
            "NumberofLinemanUsingNaanythaApp": 3,
            "NumberofCyclesCovered": 12,
            "NumberofCANsTested": 11
        },
        {
            "DivisionCode": "1",
            "SectionName": "MOGHULPURA",
            "SECTIONCODE": "0133",
            "DivisionName": "Division 1 (CHARMINAR)",
            "TestedDate": "29-08-2023",
            "TotalNumberOfLineMans": 5,
            "TotalSupplyCycles": 11,
            "TotalCans": 18,
            "NumberofLinemanUsingNaanythaApp": 1,
            "NumberofCyclesCovered": 3,
            "NumberofCANsTested": 4
        },
        {
            "DivisionCode": "1",
            "SectionName": "PATHERGATTI",
            "SECTIONCODE": "0123",
            "DivisionName": "Division 1 (CHARMINAR)",
            "TestedDate": "29-08-2023",
            "TotalNumberOfLineMans": 7,
            "TotalSupplyCycles": 21,
            "TotalCans": 58,
            "NumberofLinemanUsingNaanythaApp": 3,
            "NumberofCyclesCovered": 5,
            "NumberofCANsTested": 9
        },
        {
            "DivisionCode": "1",
            "SectionName": "VATTEPALLY",
            "SECTIONCODE": "0115",
            "DivisionName": "Division 1 (CHARMINAR)",
            "TestedDate": "",
            "TotalNumberOfLineMans": 4,
            "TotalSupplyCycles": 11,
            "TotalCans": 18,
            "NumberofLinemanUsingNaanythaApp": 0,
            "NumberofCyclesCovered": 0,
            "NumberofCANsTested": 0
        },
        {
            "DivisionCode": "2",
            "SectionName": "ASMANGARH",
            "SECTIONCODE": "0222",
            "DivisionName": "Division 2 (a) (ASMANGADH)",
            "TestedDate": "29-08-2023",
            "TotalNumberOfLineMans": 6,
            "TotalSupplyCycles": 14,
            "TotalCans": 36,
            "NumberofLinemanUsingNaanythaApp": 1,
            "NumberofCyclesCovered": 1,
            "NumberofCANsTested": 1
        },
        {
            "DivisionCode": "2",
            "SectionName": "AZAMPURA",
            "SECTIONCODE": "0135",
            "DivisionName": "Division 2 (a) (ASMANGADH)",
            "TestedDate": "",
            "TotalNumberOfLineMans": 5,
            "TotalSupplyCycles": 28,
            "TotalCans": 49,
            "NumberofLinemanUsingNaanythaApp": 0,
            "NumberofCyclesCovered": 0,
            "NumberofCANsTested": 0
        },
        {
            "DivisionCode": "2",
            "SectionName": "CHANCHALGUDA",
            "SECTIONCODE": "0223",
            "DivisionName": "Division 2 (a) (ASMANGADH)",
            "TestedDate": "29-08-2023",
            "TotalNumberOfLineMans": 1,
            "TotalSupplyCycles": 1,
            "TotalCans": 4,
            "NumberofLinemanUsingNaanythaApp": 1,
            "NumberofCyclesCovered": 1,
            "NumberofCANsTested": 1
        },
        {
            "DivisionCode": "2",
            "SectionName": "MADANNAPET",
            "SECTIONCODE": "0232",
            "DivisionName": "Division 2 (a) (ASMANGADH)",
            "TestedDate": "29-08-2023",
            "TotalNumberOfLineMans": 10,
            "TotalSupplyCycles": 17,
            "TotalCans": 67,
            "NumberofLinemanUsingNaanythaApp": 2,
            "NumberofCyclesCovered": 2,
            "NumberofCANsTested": 5
        },
        {
            "DivisionCode": "2",
            "SectionName": "MALAKPET",
            "SECTIONCODE": "0211",
            "DivisionName": "Division 2 (a) (ASMANGADH)",
            "TestedDate": "29-08-2023",
            "TotalNumberOfLineMans": 6,
            "TotalSupplyCycles": 7,
            "TotalCans": 20,
            "NumberofLinemanUsingNaanythaApp": 3,
            "NumberofCyclesCovered": 4,
            "NumberofCANsTested": 3
        },
        {
            "DivisionCode": "2",
            "SectionName": "MOOSARAMBAGH",
            "SECTIONCODE": "0213",
            "DivisionName": "Division 2 (a) (ASMANGADH)",
            "TestedDate": "29-08-2023",
            "TotalNumberOfLineMans": 8,
            "TotalSupplyCycles": 23,
            "TotalCans": 97,
            "NumberofLinemanUsingNaanythaApp": 1,
            "NumberofCyclesCovered": 1,
            "NumberofCANsTested": 5
        },
        {
            "DivisionCode": "2",
            "SectionName": "SAIDABAD",
            "SECTIONCODE": "0221",
            "DivisionName": "Division 2 (a) (ASMANGADH)",
            "TestedDate": "29-08-2023",
            "TotalNumberOfLineMans": 5,
            "TotalSupplyCycles": 10,
            "TotalCans": 30,
            "NumberofLinemanUsingNaanythaApp": 2,
            "NumberofCyclesCovered": 2,
            "NumberofCANsTested": 8
        },
        {
            "DivisionCode": "2",
            "SectionName": "SANTOSHNAGAR",
            "SECTIONCODE": "0231",
            "DivisionName": "Division 2 (a) (ASMANGADH)",
            "TestedDate": "",
            "TotalNumberOfLineMans": 7,
            "TotalSupplyCycles": 19,
            "TotalCans": 21,
            "NumberofLinemanUsingNaanythaApp": 0,
            "NumberofCyclesCovered": 0,
            "NumberofCANsTested": 0
        },
        {
            "DivisionCode": "2",
            "SectionName": "VINAY NAGAR (DIV 2 (a))",
            "SECTIONCODE": "0237",
            "DivisionName": "Division 2 (a) (ASMANGADH)",
            "TestedDate": "",
            "TotalNumberOfLineMans": 4,
            "TotalSupplyCycles": 6,
            "TotalCans": 25,
            "NumberofLinemanUsingNaanythaApp": 0,
            "NumberofCyclesCovered": 0,
            "NumberofCANsTested": 0
        },
        {
            "DivisionCode": "2",
            "SectionName": "YAKATPURA",
            "SECTIONCODE": "0233",
            "DivisionName": "Division 2 (a) (ASMANGADH)",
            "TestedDate": "",
            "TotalNumberOfLineMans": 3,
            "TotalSupplyCycles": 6,
            "TotalCans": 7,
            "NumberofLinemanUsingNaanythaApp": 0,
            "NumberofCyclesCovered": 0,
            "NumberofCANsTested": 0
        },
        {
            "DivisionCode": "3",
            "SectionName": "AHMED NAGAR",
            "SECTIONCODE": "0347",
            "DivisionName": "Division 3 (ASIFNAGAR)",
            "TestedDate": "29-08-2023",
            "TotalNumberOfLineMans": 3,
            "TotalSupplyCycles": 11,
            "TotalCans": 38,
            "NumberofLinemanUsingNaanythaApp": 1,
            "NumberofCyclesCovered": 4,
            "NumberofCANsTested": 15
        },
        {
            "DivisionCode": "3",
            "SectionName": "ASIF NAGAR",
            "SECTIONCODE": "0334",
            "DivisionName": "Division 3 (ASIFNAGAR)",
            "TestedDate": "",
            "TotalNumberOfLineMans": 6,
            "TotalSupplyCycles": 10,
            "TotalCans": 37,
            "NumberofLinemanUsingNaanythaApp": 0,
            "NumberofCyclesCovered": 0,
            "NumberofCANsTested": 0
        },
        {
            "DivisionCode": "3",
            "SectionName": "CHINTAL BASTHI",
            "SECTIONCODE": "0348",
            "DivisionName": "Division 3 (ASIFNAGAR)",
            "TestedDate": "",
            "TotalNumberOfLineMans": 3,
            "TotalSupplyCycles": 13,
            "TotalCans": 15,
            "NumberofLinemanUsingNaanythaApp": 0,
            "NumberofCyclesCovered": 0,
            "NumberofCANsTested": 0
        },
        {
            "DivisionCode": "3",
            "SectionName": "GOLCONDA",
            "SECTIONCODE": "0312",
            "DivisionName": "Division 3 (ASIFNAGAR)",
            "TestedDate": "",
            "TotalNumberOfLineMans": 9,
            "TotalSupplyCycles": 19,
            "TotalCans": 65,
            "NumberofLinemanUsingNaanythaApp": 0,
            "NumberofCyclesCovered": 0,
            "NumberofCANsTested": 0
        },
        {
            "DivisionCode": "3",
            "SectionName": "HAKEEMPET",
            "SECTIONCODE": "0313",
            "DivisionName": "Division 3 (ASIFNAGAR)",
            "TestedDate": "",
            "TotalNumberOfLineMans": 6,
            "TotalSupplyCycles": 18,
            "TotalCans": 65,
            "NumberofLinemanUsingNaanythaApp": 0,
            "NumberofCyclesCovered": 0,
            "NumberofCANsTested": 0
        },
        {
            "DivisionCode": "3",
            "SectionName": "KAKATIYA NAGAR",
            "SECTIONCODE": "0332",
            "DivisionName": "Division 3 (ASIFNAGAR)",
            "TestedDate": "",
            "TotalNumberOfLineMans": 9,
            "TotalSupplyCycles": 19,
            "TotalCans": 53,
            "NumberofLinemanUsingNaanythaApp": 0,
            "NumberofCyclesCovered": 0,
            "NumberofCANsTested": 0
        },
        {
            "DivisionCode": "3",
            "SectionName": "KARWAN",
            "SECTIONCODE": "0342",
            "DivisionName": "Division 3 (ASIFNAGAR)",
            "TestedDate": "",
            "TotalNumberOfLineMans": 7,
            "TotalSupplyCycles": 24,
            "TotalCans": 58,
            "NumberofLinemanUsingNaanythaApp": 0,
            "NumberofCyclesCovered": 0,
            "NumberofCANsTested": 0
        },
        {
            "DivisionCode": "3",
            "SectionName": "LANGER HOUSE",
            "SECTIONCODE": "0323",
            "DivisionName": "Division 3 (ASIFNAGAR)",
            "TestedDate": "",
            "TotalNumberOfLineMans": 6,
            "TotalSupplyCycles": 19,
            "TotalCans": 64,
            "NumberofLinemanUsingNaanythaApp": 0,
            "NumberofCyclesCovered": 0,
            "NumberofCANsTested": 0
        },
        {
            "DivisionCode": "3",
            "SectionName": "MEHIDIPATNAM",
            "SECTIONCODE": "0331",
            "DivisionName": "Division 3 (ASIFNAGAR)",
            "TestedDate": "29-08-2023",
            "TotalNumberOfLineMans": 7,
            "TotalSupplyCycles": 25,
            "TotalCans": 55,
            "NumberofLinemanUsingNaanythaApp": 3,
            "NumberofCyclesCovered": 9,
            "NumberofCANsTested": 23
        },
        {
            "DivisionCode": "3",
            "SectionName": "OLD MALLEPALLY",
            "SECTIONCODE": "0341",
            "DivisionName": "Division 3 (ASIFNAGAR)",
            "TestedDate": "29-08-2023",
            "TotalNumberOfLineMans": 10,
            "TotalSupplyCycles": 13,
            "TotalCans": 32,
            "NumberofLinemanUsingNaanythaApp": 2,
            "NumberofCyclesCovered": 2,
            "NumberofCANsTested": 4
        },
        {
            "DivisionCode": "3",
            "SectionName": "SHAIKPET",
            "SECTIONCODE": "0314",
            "DivisionName": "Division 3 (ASIFNAGAR)",
            "TestedDate": "29-08-2023",
            "TotalNumberOfLineMans": 6,
            "TotalSupplyCycles": 21,
            "TotalCans": 50,
            "NumberofLinemanUsingNaanythaApp": 3,
            "NumberofCyclesCovered": 4,
            "NumberofCANsTested": 6
        },
        {
            "DivisionCode": "3",
            "SectionName": "TAPPA CHABUTRA",
            "SECTIONCODE": "0343",
            "DivisionName": "Division 3 (ASIFNAGAR)",
            "TestedDate": "29-08-2023",
            "TotalNumberOfLineMans": 9,
            "TotalSupplyCycles": 34,
            "TotalCans": 67,
            "NumberofLinemanUsingNaanythaApp": 2,
            "NumberofCyclesCovered": 12,
            "NumberofCANsTested": 10
        },
        {
            "DivisionCode": "3",
            "SectionName": "TOLI CHOWK",
            "SECTIONCODE": "0311",
            "DivisionName": "Division 3 (ASIFNAGAR)",
            "TestedDate": "29-08-2023",
            "TotalNumberOfLineMans": 4,
            "TotalSupplyCycles": 15,
            "TotalCans": 53,
            "NumberofLinemanUsingNaanythaApp": 2,
            "NumberofCyclesCovered": 6,
            "NumberofCANsTested": 12
        },
        {
            "DivisionCode": "3",
            "SectionName": "VIJAYNAGAR COLONY",
            "SECTIONCODE": "0333",
            "DivisionName": "Division 3 (ASIFNAGAR)",
            "TestedDate": "29-08-2023",
            "TotalNumberOfLineMans": 8,
            "TotalSupplyCycles": 17,
            "TotalCans": 51,
            "NumberofLinemanUsingNaanythaApp": 1,
            "NumberofCyclesCovered": 1,
            "NumberofCANsTested": 1
        },
        {
            "DivisionCode": "4",
            "SectionName": "ALLABANDA",
            "SECTIONCODE": "0412",
            "DivisionName": "Division 4 (RED HILLS)",
            "TestedDate": "",
            "TotalNumberOfLineMans": 13,
            "TotalSupplyCycles": 64,
            "TotalCans": 168,
            "NumberofLinemanUsingNaanythaApp": 0,
            "NumberofCyclesCovered": 0,
            "NumberofCANsTested": 0
        },
        {
            "DivisionCode": "4",
            "SectionName": "GODE-KI-KABAR",
            "SECTIONCODE": "0421",
            "DivisionName": "Division 4 (RED HILLS)",
            "TestedDate": "",
            "TotalNumberOfLineMans": 2,
            "TotalSupplyCycles": 14,
            "TotalCans": 27,
            "NumberofLinemanUsingNaanythaApp": 0,
            "NumberofCyclesCovered": 0,
            "NumberofCANsTested": 0
        },
        {
            "DivisionCode": "4",
            "SectionName": "GOWLIGUDA",
            "SECTIONCODE": "0422",
            "DivisionName": "Division 4 (RED HILLS)",
            "TestedDate": "29-08-2023",
            "TotalNumberOfLineMans": 6,
            "TotalSupplyCycles": 22,
            "TotalCans": 37,
            "NumberofLinemanUsingNaanythaApp": 1,
            "NumberofCyclesCovered": 1,
            "NumberofCANsTested": 2
        },
        {
            "DivisionCode": "4",
            "SectionName": "GUNFOUNDRY",
            "SECTIONCODE": "0433",
            "DivisionName": "Division 4 (RED HILLS)",
            "TestedDate": "29-08-2023",
            "TotalNumberOfLineMans": 6,
            "TotalSupplyCycles": 32,
            "TotalCans": 41,
            "NumberofLinemanUsingNaanythaApp": 3,
            "NumberofCyclesCovered": 8,
            "NumberofCANsTested": 4
        },
        {
            "DivisionCode": "4",
            "SectionName": "HINDI NAGAR",
            "SECTIONCODE": "0424",
            "DivisionName": "Division 4 (RED HILLS)",
            "TestedDate": "",
            "TotalNumberOfLineMans": 6,
            "TotalSupplyCycles": 26,
            "TotalCans": 75,
            "NumberofLinemanUsingNaanythaApp": 0,
            "NumberofCyclesCovered": 0,
            "NumberofCANsTested": 0
        },
        {
            "DivisionCode": "4",
            "SectionName": "RED HILLS HIGH LEVEL",
            "SECTIONCODE": "0431",
            "DivisionName": "Division 4 (RED HILLS)",
            "TestedDate": "",
            "TotalNumberOfLineMans": 6,
            "TotalSupplyCycles": 44,
            "TotalCans": 50,
            "NumberofLinemanUsingNaanythaApp": 0,
            "NumberofCyclesCovered": 0,
            "NumberofCANsTested": 0
        },
        {
            "DivisionCode": "4",
            "SectionName": "RED HILLS LOW LEVEL",
            "SECTIONCODE": "0432",
            "DivisionName": "Division 4 (RED HILLS)",
            "TestedDate": "29-08-2023",
            "TotalNumberOfLineMans": 5,
            "TotalSupplyCycles": 15,
            "TotalCans": 33,
            "NumberofLinemanUsingNaanythaApp": 1,
            "NumberofCyclesCovered": 2,
            "NumberofCANsTested": 3
        },
        {
            "DivisionCode": "4",
            "SectionName": "SULTAN BAZAR",
            "SECTIONCODE": "0423",
            "DivisionName": "Division 4 (RED HILLS)",
            "TestedDate": "29-08-2023",
            "TotalNumberOfLineMans": 10,
            "TotalSupplyCycles": 42,
            "TotalCans": 110,
            "NumberofLinemanUsingNaanythaApp": 3,
            "NumberofCyclesCovered": 5,
            "NumberofCANsTested": 18
        },
        {
            "DivisionCode": "4",
            "SectionName": "ZIAGUDA",
            "SECTIONCODE": "0411",
            "DivisionName": "Division 4 (RED HILLS)",
            "TestedDate": "29-08-2023",
            "TotalNumberOfLineMans": 8,
            "TotalSupplyCycles": 30,
            "TotalCans": 88,
            "NumberofLinemanUsingNaanythaApp": 2,
            "NumberofCyclesCovered": 9,
            "NumberofCANsTested": 34
        },
        {
            "DivisionCode": "5",
            "SectionName": "ADIKMET",
            "SECTIONCODE": "0531",
            "DivisionName": "Division 5 (NARAYANGUDA)",
            "TestedDate": "",
            "TotalNumberOfLineMans": 3,
            "TotalSupplyCycles": 6,
            "TotalCans": 24,
            "NumberofLinemanUsingNaanythaApp": 0,
            "NumberofCyclesCovered": 0,
            "NumberofCANsTested": 0
        },
        {
            "DivisionCode": "5",
            "SectionName": "AMBERPET",
            "SECTIONCODE": "0535",
            "DivisionName": "Division 5 (NARAYANGUDA)",
            "TestedDate": "29-08-2023",
            "TotalNumberOfLineMans": 4,
            "TotalSupplyCycles": 7,
            "TotalCans": 21,
            "NumberofLinemanUsingNaanythaApp": 1,
            "NumberofCyclesCovered": 1,
            "NumberofCANsTested": 3
        },
        {
            "DivisionCode": "5",
            "SectionName": "AZAMABAD",
            "SECTIONCODE": "0522",
            "DivisionName": "Division 5 (NARAYANGUDA)",
            "TestedDate": "",
            "TotalNumberOfLineMans": 5,
            "TotalSupplyCycles": 5,
            "TotalCans": 21,
            "NumberofLinemanUsingNaanythaApp": 0,
            "NumberofCyclesCovered": 0,
            "NumberofCANsTested": 0
        },
        {
            "DivisionCode": "5",
            "SectionName": "BAGH LINGAMPALLY",
            "SECTIONCODE": "0523",
            "DivisionName": "Division 5 (NARAYANGUDA)",
            "TestedDate": "29-08-2023",
            "TotalNumberOfLineMans": 8,
            "TotalSupplyCycles": 16,
            "TotalCans": 35,
            "NumberofLinemanUsingNaanythaApp": 6,
            "NumberofCyclesCovered": 7,
            "NumberofCANsTested": 4
        },
        {
            "DivisionCode": "5",
            "SectionName": "BARKATPURA",
            "SECTIONCODE": "0542",
            "DivisionName": "Division 5 (NARAYANGUDA)",
            "TestedDate": "29-08-2023",
            "TotalNumberOfLineMans": 4,
            "TotalSupplyCycles": 15,
            "TotalCans": 27,
            "NumberofLinemanUsingNaanythaApp": 1,
            "NumberofCyclesCovered": 1,
            "NumberofCANsTested": 1
        },
        {
            "DivisionCode": "5",
            "SectionName": "BOATS CLUB",
            "SECTIONCODE": "0513",
            "DivisionName": "Division 5 (NARAYANGUDA)",
            "TestedDate": "29-08-2023",
            "TotalNumberOfLineMans": 8,
            "TotalSupplyCycles": 13,
            "TotalCans": 141,
            "NumberofLinemanUsingNaanythaApp": 1,
            "NumberofCyclesCovered": 1,
            "NumberofCANsTested": 7
        },
        {
            "DivisionCode": "5",
            "SectionName": "DOMALGUDA",
            "SECTIONCODE": "0512",
            "DivisionName": "Division 5 (NARAYANGUDA)",
            "TestedDate": "29-08-2023",
            "TotalNumberOfLineMans": 3,
            "TotalSupplyCycles": 18,
            "TotalCans": 28,
            "NumberofLinemanUsingNaanythaApp": 3,
            "NumberofCyclesCovered": 6,
            "NumberofCANsTested": 13
        },
        {
            "DivisionCode": "5",
            "SectionName": "GANDHINAGAR",
            "SECTIONCODE": "0511",
            "DivisionName": "Division 5 (NARAYANGUDA)",
            "TestedDate": "29-08-2023",
            "TotalNumberOfLineMans": 6,
            "TotalSupplyCycles": 21,
            "TotalCans": 57,
            "NumberofLinemanUsingNaanythaApp": 3,
            "NumberofCyclesCovered": 6,
            "NumberofCANsTested": 9
        },
        {
            "DivisionCode": "5",
            "SectionName": "MUSHEERABAD",
            "SECTIONCODE": "0521",
            "DivisionName": "Division 5 (NARAYANGUDA)",
            "TestedDate": "",
            "TotalNumberOfLineMans": 4,
            "TotalSupplyCycles": 17,
            "TotalCans": 63,
            "NumberofLinemanUsingNaanythaApp": 0,
            "NumberofCyclesCovered": 0,
            "NumberofCANsTested": 0
        },
        {
            "DivisionCode": "5",
            "SectionName": "NARAYANGUDA",
            "SECTIONCODE": "0541",
            "DivisionName": "Division 5 (NARAYANGUDA)",
            "TestedDate": "",
            "TotalNumberOfLineMans": 9,
            "TotalSupplyCycles": 39,
            "TotalCans": 138,
            "NumberofLinemanUsingNaanythaApp": 0,
            "NumberofCyclesCovered": 0,
            "NumberofCANsTested": 0
        },
        {
            "DivisionCode": "5",
            "SectionName": "SHIVAM",
            "SECTIONCODE": "0532",
            "DivisionName": "Division 5 (NARAYANGUDA)",
            "TestedDate": "29-08-2023",
            "TotalNumberOfLineMans": 10,
            "TotalSupplyCycles": 18,
            "TotalCans": 73,
            "NumberofLinemanUsingNaanythaApp": 1,
            "NumberofCyclesCovered": 1,
            "NumberofCANsTested": 6
        },
        {
            "DivisionCode": "5",
            "SectionName": "VIGYANPURI",
            "SECTIONCODE": "0533",
            "DivisionName": "Division 5 (NARAYANGUDA)",
            "TestedDate": "",
            "TotalNumberOfLineMans": 7,
            "TotalSupplyCycles": 22,
            "TotalCans": 40,
            "NumberofLinemanUsingNaanythaApp": 0,
            "NumberofCyclesCovered": 0,
            "NumberofCANsTested": 0
        },
        {
            "DivisionCode": "6",
            "SectionName": "BANJARA HILLS",
            "SECTIONCODE": "0612",
            "DivisionName": "Division 6 (S.R.NAGAR)",
            "TestedDate": "29-08-2023",
            "TotalNumberOfLineMans": 13,
            "TotalSupplyCycles": 129,
            "TotalCans": 148,
            "NumberofLinemanUsingNaanythaApp": 4,
            "NumberofCyclesCovered": 23,
            "NumberofCANsTested": 46
        },
        {
            "DivisionCode": "6",
            "SectionName": "BORABANDA",
            "SECTIONCODE": "0625",
            "DivisionName": "Division 6 (S.R.NAGAR)",
            "TestedDate": "",
            "TotalNumberOfLineMans": 7,
            "TotalSupplyCycles": 33,
            "TotalCans": 64,
            "NumberofLinemanUsingNaanythaApp": 0,
            "NumberofCyclesCovered": 0,
            "NumberofCANsTested": 0
        },
        {
            "DivisionCode": "6",
            "SectionName": "ERRAGADDA",
            "SECTIONCODE": "0623",
            "DivisionName": "Division 6 (S.R.NAGAR)",
            "TestedDate": "29-08-2023",
            "TotalNumberOfLineMans": 8,
            "TotalSupplyCycles": 59,
            "TotalCans": 57,
            "NumberofLinemanUsingNaanythaApp": 1,
            "NumberofCyclesCovered": 3,
            "NumberofCANsTested": 3
        },
        {
            "DivisionCode": "6",
            "SectionName": "FATHENAGAR",
            "SECTIONCODE": "0622",
            "DivisionName": "Division 6 (S.R.NAGAR)",
            "TestedDate": "29-08-2023",
            "TotalNumberOfLineMans": 8,
            "TotalSupplyCycles": 39,
            "TotalCans": 41,
            "NumberofLinemanUsingNaanythaApp": 4,
            "NumberofCyclesCovered": 10,
            "NumberofCANsTested": 12
        },
        {
            "DivisionCode": "6",
            "SectionName": "FILM NAGAR",
            "SECTIONCODE": "0615",
            "DivisionName": "Division 6 (S.R.NAGAR)",
            "TestedDate": "29-08-2023",
            "TotalNumberOfLineMans": 7,
            "TotalSupplyCycles": 57,
            "TotalCans": 83,
            "NumberofLinemanUsingNaanythaApp": 4,
            "NumberofCyclesCovered": 16,
            "NumberofCANsTested": 25
        },
        {
            "DivisionCode": "6",
            "SectionName": "JUBILEE HILLS",
            "SECTIONCODE": "0611",
            "DivisionName": "Division 6 (S.R.NAGAR)",
            "TestedDate": "",
            "TotalNumberOfLineMans": 8,
            "TotalSupplyCycles": 62,
            "TotalCans": 88,
            "NumberofLinemanUsingNaanythaApp": 0,
            "NumberofCyclesCovered": 0,
            "NumberofCANsTested": 0
        },
        {
            "DivisionCode": "6",
            "SectionName": "S.P.R HILLS",
            "SECTIONCODE": "0633",
            "DivisionName": "Division 6 (S.R.NAGAR)",
            "TestedDate": "",
            "TotalNumberOfLineMans": 5,
            "TotalSupplyCycles": 33,
            "TotalCans": 53,
            "NumberofLinemanUsingNaanythaApp": 0,
            "NumberofCyclesCovered": 0,
            "NumberofCANsTested": 0
        },
        {
            "DivisionCode": "6",
            "SectionName": "S.R.NAGAR",
            "SECTIONCODE": "0624",
            "DivisionName": "Division 6 (S.R.NAGAR)",
            "TestedDate": "",
            "TotalNumberOfLineMans": 6,
            "TotalSupplyCycles": 20,
            "TotalCans": 37,
            "NumberofLinemanUsingNaanythaApp": 0,
            "NumberofCyclesCovered": 0,
            "NumberofCANsTested": 0
        },
        {
            "DivisionCode": "6",
            "SectionName": "SOMAJIGUDA",
            "SECTIONCODE": "0621",
            "DivisionName": "Division 6 (S.R.NAGAR)",
            "TestedDate": "29-08-2023",
            "TotalNumberOfLineMans": 10,
            "TotalSupplyCycles": 24,
            "TotalCans": 25,
            "NumberofLinemanUsingNaanythaApp": 2,
            "NumberofCyclesCovered": 3,
            "NumberofCANsTested": 3
        },
        {
            "DivisionCode": "6",
            "SectionName": "THATTIKHANA",
            "SECTIONCODE": "0613",
            "DivisionName": "Division 6 (S.R.NAGAR)",
            "TestedDate": "29-08-2023",
            "TotalNumberOfLineMans": 13,
            "TotalSupplyCycles": 79,
            "TotalCans": 104,
            "NumberofLinemanUsingNaanythaApp": 5,
            "NumberofCyclesCovered": 18,
            "NumberofCANsTested": 34
        },
        {
            "DivisionCode": "6",
            "SectionName": "VENGALRAONAGAR",
            "SECTIONCODE": "0632",
            "DivisionName": "Division 6 (S.R.NAGAR)",
            "TestedDate": "29-08-2023",
            "TotalNumberOfLineMans": 5,
            "TotalSupplyCycles": 24,
            "TotalCans": 25,
            "NumberofLinemanUsingNaanythaApp": 2,
            "NumberofCyclesCovered": 3,
            "NumberofCANsTested": 6
        },
        {
            "DivisionCode": "6",
            "SectionName": "YELLAREDDYGUDA",
            "SECTIONCODE": "0631",
            "DivisionName": "Division 6 (S.R.NAGAR)",
            "TestedDate": "29-08-2023",
            "TotalNumberOfLineMans": 11,
            "TotalSupplyCycles": 26,
            "TotalCans": 44,
            "NumberofLinemanUsingNaanythaApp": 2,
            "NumberofCyclesCovered": 2,
            "NumberofCANsTested": 6
        },
        {
            "DivisionCode": "7",
            "SectionName": "BOIGUDA",
            "SECTIONCODE": "0712",
            "DivisionName": "Division 7 (MARREDPALLY)",
            "TestedDate": "29-08-2023",
            "TotalNumberOfLineMans": 7,
            "TotalSupplyCycles": 9,
            "TotalCans": 44,
            "NumberofLinemanUsingNaanythaApp": 1,
            "NumberofCyclesCovered": 1,
            "NumberofCANsTested": 2
        },
        {
            "DivisionCode": "7",
            "SectionName": "BOUDHANAGAR",
            "SECTIONCODE": "0726",
            "DivisionName": "Division 7 (MARREDPALLY)",
            "TestedDate": "29-08-2023",
            "TotalNumberOfLineMans": 4,
            "TotalSupplyCycles": 27,
            "TotalCans": 96,
            "NumberofLinemanUsingNaanythaApp": 1,
            "NumberofCyclesCovered": 5,
            "NumberofCANsTested": 18
        },
        {
            "DivisionCode": "7",
            "SectionName": "HUSSAINSAGAR",
            "SECTIONCODE": "0711",
            "DivisionName": "Division 7 (MARREDPALLY)",
            "TestedDate": "29-08-2023",
            "TotalNumberOfLineMans": 5,
            "TotalSupplyCycles": 15,
            "TotalCans": 48,
            "NumberofLinemanUsingNaanythaApp": 1,
            "NumberofCyclesCovered": 3,
            "NumberofCANsTested": 4
        },
        {
            "DivisionCode": "7",
            "SectionName": "LALAPET",
            "SECTIONCODE": "0733",
            "DivisionName": "Division 7 (MARREDPALLY)",
            "TestedDate": "29-08-2023",
            "TotalNumberOfLineMans": 4,
            "TotalSupplyCycles": 36,
            "TotalCans": 45,
            "NumberofLinemanUsingNaanythaApp": 2,
            "NumberofCyclesCovered": 12,
            "NumberofCANsTested": 10
        },
        {
            "DivisionCode": "7",
            "SectionName": "MARREDPALLY",
            "SECTIONCODE": "0722",
            "DivisionName": "Division 7 (MARREDPALLY)",
            "TestedDate": "29-08-2023",
            "TotalNumberOfLineMans": 9,
            "TotalSupplyCycles": 74,
            "TotalCans": 208,
            "NumberofLinemanUsingNaanythaApp": 1,
            "NumberofCyclesCovered": 9,
            "NumberofCANsTested": 18
        },
        {
            "DivisionCode": "7",
            "SectionName": "METTUGUDA",
            "SECTIONCODE": "0723",
            "DivisionName": "Division 7 (MARREDPALLY)",
            "TestedDate": "",
            "TotalNumberOfLineMans": 4,
            "TotalSupplyCycles": 12,
            "TotalCans": 79,
            "NumberofLinemanUsingNaanythaApp": 0,
            "NumberofCyclesCovered": 0,
            "NumberofCANsTested": 0
        },
        {
            "DivisionCode": "7",
            "SectionName": "NALLAGUTTA",
            "SECTIONCODE": "0642",
            "DivisionName": "Division 7 (MARREDPALLY)",
            "TestedDate": "29-08-2023",
            "TotalNumberOfLineMans": 4,
            "TotalSupplyCycles": 10,
            "TotalCans": 48,
            "NumberofLinemanUsingNaanythaApp": 2,
            "NumberofCyclesCovered": 3,
            "NumberofCANsTested": 19
        },
        {
            "DivisionCode": "7",
            "SectionName": "PRAKASHNAGAR",
            "SECTIONCODE": "0641",
            "DivisionName": "Division 7 (MARREDPALLY)",
            "TestedDate": "29-08-2023",
            "TotalNumberOfLineMans": 6,
            "TotalSupplyCycles": 51,
            "TotalCans": 88,
            "NumberofLinemanUsingNaanythaApp": 3,
            "NumberofCyclesCovered": 18,
            "NumberofCANsTested": 29
        },
        {
            "DivisionCode": "7",
            "SectionName": "REGIMENTAL BAZAR",
            "SECTIONCODE": "0721",
            "DivisionName": "Division 7 (MARREDPALLY)",
            "TestedDate": "29-08-2023",
            "TotalNumberOfLineMans": 4,
            "TotalSupplyCycles": 8,
            "TotalCans": 22,
            "NumberofLinemanUsingNaanythaApp": 1,
            "NumberofCyclesCovered": 2,
            "NumberofCANsTested": 8
        },
        {
            "DivisionCode": "7",
            "SectionName": "SEETHAPALMANDI",
            "SECTIONCODE": "0724",
            "DivisionName": "Division 7 (MARREDPALLY)",
            "TestedDate": "",
            "TotalNumberOfLineMans": 6,
            "TotalSupplyCycles": 16,
            "TotalCans": 85,
            "NumberofLinemanUsingNaanythaApp": 0,
            "NumberofCyclesCovered": 0,
            "NumberofCANsTested": 0
        },
        {
            "DivisionCode": "7",
            "SectionName": "SRINIVAS NAGAR",
            "SECTIONCODE": "0714",
            "DivisionName": "Division 7 (MARREDPALLY)",
            "TestedDate": "29-08-2023",
            "TotalNumberOfLineMans": 6,
            "TotalSupplyCycles": 18,
            "TotalCans": 44,
            "NumberofLinemanUsingNaanythaApp": 5,
            "NumberofCyclesCovered": 11,
            "NumberofCANsTested": 20
        },
        {
            "DivisionCode": "7",
            "SectionName": "TARNAKA",
            "SECTIONCODE": "0732",
            "DivisionName": "Division 7 (MARREDPALLY)",
            "TestedDate": "",
            "TotalNumberOfLineMans": 6,
            "TotalSupplyCycles": 27,
            "TotalCans": 111,
            "NumberofLinemanUsingNaanythaApp": 0,
            "NumberofCyclesCovered": 0,
            "NumberofCANsTested": 0
        },
        {
            "DivisionCode": "9",
            "SectionName": "BALAJINAGAR (DIV 9)",
            "SECTIONCODE": "0925",
            "DivisionName": "Division 9 (KUKATPALLY)",
            "TestedDate": "29-08-2023",
            "TotalNumberOfLineMans": 9,
            "TotalSupplyCycles": 38,
            "TotalCans": 157,
            "NumberofLinemanUsingNaanythaApp": 2,
            "NumberofCyclesCovered": 5,
            "NumberofCANsTested": 16
        },
        {
            "DivisionCode": "9",
            "SectionName": "BALANAGAR",
            "SECTIONCODE": "0912",
            "DivisionName": "Division 9 (KUKATPALLY)",
            "TestedDate": "29-08-2023",
            "TotalNumberOfLineMans": 12,
            "TotalSupplyCycles": 42,
            "TotalCans": 106,
            "NumberofLinemanUsingNaanythaApp": 1,
            "NumberofCyclesCovered": 1,
            "NumberofCANsTested": 4
        },
        {
            "DivisionCode": "9",
            "SectionName": "BHAGYANAGAR",
            "SECTIONCODE": "0917",
            "DivisionName": "Division 9 (KUKATPALLY)",
            "TestedDate": "29-08-2023",
            "TotalNumberOfLineMans": 6,
            "TotalSupplyCycles": 39,
            "TotalCans": 117,
            "NumberofLinemanUsingNaanythaApp": 3,
            "NumberofCyclesCovered": 11,
            "NumberofCANsTested": 39
        },
        {
            "DivisionCode": "9",
            "SectionName": "BHARATHNAGAR",
            "SECTIONCODE": "0926",
            "DivisionName": "Division 9 (KUKATPALLY)",
            "TestedDate": "",
            "TotalNumberOfLineMans": 3,
            "TotalSupplyCycles": 24,
            "TotalCans": 68,
            "NumberofLinemanUsingNaanythaApp": 0,
            "NumberofCyclesCovered": 0,
            "NumberofCANsTested": 0
        },
        {
            "DivisionCode": "9",
            "SectionName": "GAYATRI NAGAR",
            "SECTIONCODE": "0928",
            "DivisionName": "Division 9 (KUKATPALLY)",
            "TestedDate": "",
            "TotalNumberOfLineMans": 6,
            "TotalSupplyCycles": 15,
            "TotalCans": 69,
            "NumberofLinemanUsingNaanythaApp": 0,
            "NumberofCyclesCovered": 0,
            "NumberofCANsTested": 0
        },
        {
            "DivisionCode": "9",
            "SectionName": "HASMATHPET",
            "SECTIONCODE": "0913",
            "DivisionName": "Division 9 (KUKATPALLY)",
            "TestedDate": "29-08-2023",
            "TotalNumberOfLineMans": 9,
            "TotalSupplyCycles": 55,
            "TotalCans": 200,
            "NumberofLinemanUsingNaanythaApp": 4,
            "NumberofCyclesCovered": 16,
            "NumberofCANsTested": 37
        },
        {
            "DivisionCode": "9",
            "SectionName": "KPHB",
            "SECTIONCODE": "0915",
            "DivisionName": "Division 9 (KUKATPALLY)",
            "TestedDate": "29-08-2023",
            "TotalNumberOfLineMans": 9,
            "TotalSupplyCycles": 41,
            "TotalCans": 162,
            "NumberofLinemanUsingNaanythaApp": 1,
            "NumberofCyclesCovered": 1,
            "NumberofCANsTested": 4
        },
        {
            "DivisionCode": "9",
            "SectionName": "KUKATPALLY",
            "SECTIONCODE": "0918",
            "DivisionName": "Division 9 (KUKATPALLY)",
            "TestedDate": "29-08-2023",
            "TotalNumberOfLineMans": 4,
            "TotalSupplyCycles": 13,
            "TotalCans": 65,
            "NumberofLinemanUsingNaanythaApp": 1,
            "NumberofCyclesCovered": 4,
            "NumberofCANsTested": 14
        },
        {
            "DivisionCode": "9",
            "SectionName": "MOOSAPET",
            "SECTIONCODE": "0911",
            "DivisionName": "Division 9 (KUKATPALLY)",
            "TestedDate": "",
            "TotalNumberOfLineMans": 3,
            "TotalSupplyCycles": 27,
            "TotalCans": 99,
            "NumberofLinemanUsingNaanythaApp": 0,
            "NumberofCyclesCovered": 0,
            "NumberofCANsTested": 0
        },
        {
            "DivisionCode": "9",
            "SectionName": "MOTI NAGAR",
            "SECTIONCODE": "0927",
            "DivisionName": "Division 9 (KUKATPALLY)",
            "TestedDate": "29-08-2023",
            "TotalNumberOfLineMans": 3,
            "TotalSupplyCycles": 24,
            "TotalCans": 74,
            "NumberofLinemanUsingNaanythaApp": 1,
            "NumberofCyclesCovered": 6,
            "NumberofCANsTested": 13
        },
        {
            "DivisionCode": "9",
            "SectionName": "VIVEKANANDA NAGAR",
            "SECTIONCODE": "0919",
            "DivisionName": "Division 9 (KUKATPALLY)",
            "TestedDate": "29-08-2023",
            "TotalNumberOfLineMans": 7,
            "TotalSupplyCycles": 27,
            "TotalCans": 99,
            "NumberofLinemanUsingNaanythaApp": 1,
            "NumberofCyclesCovered": 2,
            "NumberofCANsTested": 6
        },
        {
            "DivisionCode": "9",
            "SectionName": "YELLAMMABANDA",
            "SECTIONCODE": "0920",
            "DivisionName": "Division 9 (KUKATPALLY)",
            "TestedDate": "29-08-2023",
            "TotalNumberOfLineMans": 4,
            "TotalSupplyCycles": 24,
            "TotalCans": 92,
            "NumberofLinemanUsingNaanythaApp": 1,
            "NumberofCyclesCovered": 1,
            "NumberofCANsTested": 3
        },
        {
            "DivisionCode": "10",
            "SectionName": "ALKAPURI",
            "SECTIONCODE": "0244",
            "DivisionName": "Division 10 (a) (L.B.NAGAR)",
            "TestedDate": "",
            "TotalNumberOfLineMans": 7,
            "TotalSupplyCycles": 38,
            "TotalCans": 84,
            "NumberofLinemanUsingNaanythaApp": 0,
            "NumberofCyclesCovered": 0,
            "NumberofCANsTested": 0
        },
        {
            "DivisionCode": "10",
            "SectionName": "DILSHUKNAGAR",
            "SECTIONCODE": "0242",
            "DivisionName": "Division 10 (a) (L.B.NAGAR)",
            "TestedDate": "29-08-2023",
            "TotalNumberOfLineMans": 7,
            "TotalSupplyCycles": 17,
            "TotalCans": 57,
            "NumberofLinemanUsingNaanythaApp": 1,
            "NumberofCyclesCovered": 2,
            "NumberofCANsTested": 7
        },
        {
            "DivisionCode": "10",
            "SectionName": "KOTHAPETA",
            "SECTIONCODE": "1022",
            "DivisionName": "Division 10 (a) (L.B.NAGAR)",
            "TestedDate": "29-08-2023",
            "TotalNumberOfLineMans": 6,
            "TotalSupplyCycles": 22,
            "TotalCans": 54,
            "NumberofLinemanUsingNaanythaApp": 4,
            "NumberofCyclesCovered": 8,
            "NumberofCANsTested": 9
        },
        {
            "DivisionCode": "10",
            "SectionName": "LINGOJIGUDA",
            "SECTIONCODE": "1012",
            "DivisionName": "Division 10 (a) (L.B.NAGAR)",
            "TestedDate": "29-08-2023",
            "TotalNumberOfLineMans": 9,
            "TotalSupplyCycles": 47,
            "TotalCans": 153,
            "NumberofLinemanUsingNaanythaApp": 1,
            "NumberofCyclesCovered": 1,
            "NumberofCANsTested": 3
        },
        {
            "DivisionCode": "10",
            "SectionName": "MARUTHINAGAR (DIV 10)",
            "SECTIONCODE": "1031",
            "DivisionName": "Division 10 (a) (L.B.NAGAR)",
            "TestedDate": "29-08-2023",
            "TotalNumberOfLineMans": 5,
            "TotalSupplyCycles": 25,
            "TotalCans": 87,
            "NumberofLinemanUsingNaanythaApp": 1,
            "NumberofCyclesCovered": 3,
            "NumberofCANsTested": 11
        },
        {
            "DivisionCode": "10",
            "SectionName": "SAHEBNAGAR (DIV 10)",
            "SECTIONCODE": "1021",
            "DivisionName": "Division 10 (a) (L.B.NAGAR)",
            "TestedDate": "",
            "TotalNumberOfLineMans": 8,
            "TotalSupplyCycles": 27,
            "TotalCans": 92,
            "NumberofLinemanUsingNaanythaApp": 0,
            "NumberofCyclesCovered": 0,
            "NumberofCANsTested": 0
        },
        {
            "DivisionCode": "10",
            "SectionName": "SAROORNAGAR",
            "SECTIONCODE": "0241",
            "DivisionName": "Division 10 (a) (L.B.NAGAR)",
            "TestedDate": "29-08-2023",
            "TotalNumberOfLineMans": 5,
            "TotalSupplyCycles": 46,
            "TotalCans": 126,
            "NumberofLinemanUsingNaanythaApp": 1,
            "NumberofCyclesCovered": 2,
            "NumberofCANsTested": 6
        },
        {
            "DivisionCode": "10",
            "SectionName": "VAISHALINAGAR (DIV 10)",
            "SECTIONCODE": "1011",
            "DivisionName": "Division 10 (a) (L.B.NAGAR)",
            "TestedDate": "29-08-2023",
            "TotalNumberOfLineMans": 12,
            "TotalSupplyCycles": 45,
            "TotalCans": 171,
            "NumberofLinemanUsingNaanythaApp": 1,
            "NumberofCyclesCovered": 3,
            "NumberofCANsTested": 6
        },
        {
            "DivisionCode": "12",
            "SectionName": "ADARSHNAGAR",
            "SECTIONCODE": "0923",
            "DivisionName": "Division 12 (QUTHUBULLAPUR)",
            "TestedDate": "29-08-2023",
            "TotalNumberOfLineMans": 3,
            "TotalSupplyCycles": 17,
            "TotalCans": 29,
            "NumberofLinemanUsingNaanythaApp": 1,
            "NumberofCyclesCovered": 8,
            "NumberofCANsTested": 13
        },
        {
            "DivisionCode": "12",
            "SectionName": "Bhagatsingh Nagar",
            "SECTIONCODE": "1214",
            "DivisionName": "Division 12 (QUTHUBULLAPUR)",
            "TestedDate": "29-08-2023",
            "TotalNumberOfLineMans": 4,
            "TotalSupplyCycles": 26,
            "TotalCans": 83,
            "NumberofLinemanUsingNaanythaApp": 1,
            "NumberofCyclesCovered": 3,
            "NumberofCANsTested": 15
        },
        {
            "DivisionCode": "12",
            "SectionName": "CHINTAL",
            "SECTIONCODE": "0922",
            "DivisionName": "Division 12 (QUTHUBULLAPUR)",
            "TestedDate": "29-08-2023",
            "TotalNumberOfLineMans": 5,
            "TotalSupplyCycles": 31,
            "TotalCans": 220,
            "NumberofLinemanUsingNaanythaApp": 2,
            "NumberofCyclesCovered": 6,
            "NumberofCANsTested": 36
        },
        {
            "DivisionCode": "12",
            "SectionName": "GAJULARAMARAM",
            "SECTIONCODE": "1221",
            "DivisionName": "Division 12 (QUTHUBULLAPUR)",
            "TestedDate": "29-08-2023",
            "TotalNumberOfLineMans": 6,
            "TotalSupplyCycles": 22,
            "TotalCans": 53,
            "NumberofLinemanUsingNaanythaApp": 3,
            "NumberofCyclesCovered": 5,
            "NumberofCANsTested": 6
        },
        {
            "DivisionCode": "12",
            "SectionName": "JEEDIMETLA",
            "SECTIONCODE": "0924",
            "DivisionName": "Division 12 (QUTHUBULLAPUR)",
            "TestedDate": "",
            "TotalNumberOfLineMans": 5,
            "TotalSupplyCycles": 41,
            "TotalCans": 171,
            "NumberofLinemanUsingNaanythaApp": 0,
            "NumberofCyclesCovered": 0,
            "NumberofCANsTested": 0
        },
        {
            "DivisionCode": "12",
            "SectionName": "Jagathgirigutta",
            "SECTIONCODE": "1213",
            "DivisionName": "Division 12 (QUTHUBULLAPUR)",
            "TestedDate": "29-08-2023",
            "TotalNumberOfLineMans": 3,
            "TotalSupplyCycles": 22,
            "TotalCans": 41,
            "NumberofLinemanUsingNaanythaApp": 1,
            "NumberofCyclesCovered": 3,
            "NumberofCANsTested": 11
        },
        {
            "DivisionCode": "12",
            "SectionName": "SHAPOORNAGAR",
            "SECTIONCODE": "0921",
            "DivisionName": "Division 12 (QUTHUBULLAPUR)",
            "TestedDate": "29-08-2023",
            "TotalNumberOfLineMans": 5,
            "TotalSupplyCycles": 44,
            "TotalCans": 57,
            "NumberofLinemanUsingNaanythaApp": 2,
            "NumberofCyclesCovered": 7,
            "NumberofCANsTested": 9
        },
        {
            "DivisionCode": "12",
            "SectionName": "SURARAM",
            "SECTIONCODE": "1223",
            "DivisionName": "Division 12 (QUTHUBULLAPUR)",
            "TestedDate": "29-08-2023",
            "TotalNumberOfLineMans": 7,
            "TotalSupplyCycles": 13,
            "TotalCans": 204,
            "NumberofLinemanUsingNaanythaApp": 2,
            "NumberofCyclesCovered": 3,
            "NumberofCANsTested": 37
        },
        {
            "DivisionCode": "12",
            "SectionName": "USHODAYA",
            "SECTIONCODE": "1222",
            "DivisionName": "Division 12 (QUTHUBULLAPUR)",
            "TestedDate": "",
            "TotalNumberOfLineMans": 3,
            "TotalSupplyCycles": 84,
            "TotalCans": 103,
            "NumberofLinemanUsingNaanythaApp": 0,
            "NumberofCyclesCovered": 0,
            "NumberofCANsTested": 0
        },
        {
            "DivisionCode": "12",
            "SectionName": "suchitra",
            "SECTIONCODE": "1212",
            "DivisionName": "Division 12 (QUTHUBULLAPUR)",
            "TestedDate": "29-08-2023",
            "TotalNumberOfLineMans": 5,
            "TotalSupplyCycles": 47,
            "TotalCans": 89,
            "NumberofLinemanUsingNaanythaApp": 1,
            "NumberofCyclesCovered": 1,
            "NumberofCANsTested": 1
        },
        {
            "DivisionCode": "13",
            "SectionName": "ALWAL (Div13)",
            "SECTIONCODE": "1301",
            "DivisionName": "Division 13 (ALWAL N MALKAJGIRI)",
            "TestedDate": "29-08-2023",
            "TotalNumberOfLineMans": 6,
            "TotalSupplyCycles": 41,
            "TotalCans": 116,
            "NumberofLinemanUsingNaanythaApp": 2,
            "NumberofCyclesCovered": 10,
            "NumberofCANsTested": 27
        },
        {
            "DivisionCode": "13",
            "SectionName": "CHANUKYAPURI",
            "SECTIONCODE": "1324",
            "DivisionName": "Division 13 (ALWAL N MALKAJGIRI)",
            "TestedDate": "29-08-2023",
            "TotalNumberOfLineMans": 9,
            "TotalSupplyCycles": 47,
            "TotalCans": 174,
            "NumberofLinemanUsingNaanythaApp": 2,
            "NumberofCyclesCovered": 5,
            "NumberofCANsTested": 18
        },
        {
            "DivisionCode": "13",
            "SectionName": "DEFENCE COLONY",
            "SECTIONCODE": "1321",
            "DivisionName": "Division 13 (ALWAL N MALKAJGIRI)",
            "TestedDate": "29-08-2023",
            "TotalNumberOfLineMans": 12,
            "TotalSupplyCycles": 63,
            "TotalCans": 195,
            "NumberofLinemanUsingNaanythaApp": 1,
            "NumberofCyclesCovered": 3,
            "NumberofCANsTested": 6
        },
        {
            "DivisionCode": "13",
            "SectionName": "FATHER BALAIAHNAGAR (Div13)",
            "SECTIONCODE": "1302",
            "DivisionName": "Division 13 (ALWAL N MALKAJGIRI)",
            "TestedDate": "",
            "TotalNumberOfLineMans": 3,
            "TotalSupplyCycles": 18,
            "TotalCans": 35,
            "NumberofLinemanUsingNaanythaApp": 0,
            "NumberofCyclesCovered": 0,
            "NumberofCANsTested": 0
        },
        {
            "DivisionCode": "13",
            "SectionName": "GOWTHAM NAGAR",
            "SECTIONCODE": "1323",
            "DivisionName": "Division 13 (ALWAL N MALKAJGIRI)",
            "TestedDate": "29-08-2023",
            "TotalNumberOfLineMans": 7,
            "TotalSupplyCycles": 37,
            "TotalCans": 136,
            "NumberofLinemanUsingNaanythaApp": 1,
            "NumberofCyclesCovered": 2,
            "NumberofCANsTested": 7
        },
        {
            "DivisionCode": "13",
            "SectionName": "MACHABOLLARAM",
            "SECTIONCODE": "1312",
            "DivisionName": "Division 13 (ALWAL N MALKAJGIRI)",
            "TestedDate": "29-08-2023",
            "TotalNumberOfLineMans": 4,
            "TotalSupplyCycles": 26,
            "TotalCans": 50,
            "NumberofLinemanUsingNaanythaApp": 1,
            "NumberofCyclesCovered": 1,
            "NumberofCANsTested": 4
        },
        {
            "DivisionCode": "13",
            "SectionName": "SAINATHPURAM",
            "SECTIONCODE": "1322",
            "DivisionName": "Division 13 (ALWAL N MALKAJGIRI)",
            "TestedDate": "29-08-2023",
            "TotalNumberOfLineMans": 9,
            "TotalSupplyCycles": 58,
            "TotalCans": 170,
            "NumberofLinemanUsingNaanythaApp": 4,
            "NumberofCyclesCovered": 15,
            "NumberofCANsTested": 41
        },
        {
            "DivisionCode": "13",
            "SectionName": "VAJPAYEE NAGAR",
            "SECTIONCODE": "1325",
            "DivisionName": "Division 13 (ALWAL N MALKAJGIRI)",
            "TestedDate": "29-08-2023",
            "TotalNumberOfLineMans": 10,
            "TotalSupplyCycles": 55,
            "TotalCans": 158,
            "NumberofLinemanUsingNaanythaApp": 2,
            "NumberofCyclesCovered": 7,
            "NumberofCANsTested": 19
        },
        {
            "DivisionCode": "13",
            "SectionName": "VENKATAPURAM",
            "SECTIONCODE": "1311",
            "DivisionName": "Division 13 (ALWAL N MALKAJGIRI)",
            "TestedDate": "",
            "TotalNumberOfLineMans": 6,
            "TotalSupplyCycles": 99,
            "TotalCans": 165,
            "NumberofLinemanUsingNaanythaApp": 0,
            "NumberofCyclesCovered": 0,
            "NumberofCANsTested": 0
        },
        {
            "DivisionCode": "13",
            "SectionName": "YAPRAL (Div13)",
            "SECTIONCODE": "1303",
            "DivisionName": "Division 13 (ALWAL N MALKAJGIRI)",
            "TestedDate": "29-08-2023",
            "TotalNumberOfLineMans": 5,
            "TotalSupplyCycles": 41,
            "TotalCans": 126,
            "NumberofLinemanUsingNaanythaApp": 1,
            "NumberofCyclesCovered": 8,
            "NumberofCANsTested": 29
        },
        {
            "DivisionCode": "14",
            "SectionName": "CHERLAPALLY",
            "SECTIONCODE": "1414",
            "DivisionName": "Division 14 (KAPRA N UPPAL)",
            "TestedDate": "",
            "TotalNumberOfLineMans": 5,
            "TotalSupplyCycles": 39,
            "TotalCans": 36,
            "NumberofLinemanUsingNaanythaApp": 0,
            "NumberofCyclesCovered": 0,
            "NumberofCANsTested": 0
        },
        {
            "DivisionCode": "14",
            "SectionName": "HOUSING BOARD",
            "SECTIONCODE": "1412",
            "DivisionName": "Division 14 (KAPRA N UPPAL)",
            "TestedDate": "29-08-2023",
            "TotalNumberOfLineMans": 12,
            "TotalSupplyCycles": 71,
            "TotalCans": 91,
            "NumberofLinemanUsingNaanythaApp": 8,
            "NumberofCyclesCovered": 26,
            "NumberofCANsTested": 34
        },
        {
            "DivisionCode": "14",
            "SectionName": "HUBSIGUDA",
            "SECTIONCODE": "1421",
            "DivisionName": "Division 14 (KAPRA N UPPAL)",
            "TestedDate": "29-08-2023",
            "TotalNumberOfLineMans": 7,
            "TotalSupplyCycles": 17,
            "TotalCans": 56,
            "NumberofLinemanUsingNaanythaApp": 1,
            "NumberofCyclesCovered": 2,
            "NumberofCANsTested": 11
        },
        {
            "DivisionCode": "14",
            "SectionName": "NACHARAM",
            "SECTIONCODE": "1415",
            "DivisionName": "Division 14 (KAPRA N UPPAL)",
            "TestedDate": "29-08-2023",
            "TotalNumberOfLineMans": 10,
            "TotalSupplyCycles": 55,
            "TotalCans": 147,
            "NumberofLinemanUsingNaanythaApp": 4,
            "NumberofCyclesCovered": 12,
            "NumberofCANsTested": 32
        },
        {
            "DivisionCode": "14",
            "SectionName": "RADHIKA",
            "SECTIONCODE": "1411",
            "DivisionName": "Division 14 (KAPRA N UPPAL)",
            "TestedDate": "",
            "TotalNumberOfLineMans": 8,
            "TotalSupplyCycles": 46,
            "TotalCans": 47,
            "NumberofLinemanUsingNaanythaApp": 0,
            "NumberofCyclesCovered": 0,
            "NumberofCANsTested": 0
        },
        {
            "DivisionCode": "14",
            "SectionName": "RAMANTHAPUR(DIV 14)",
            "SECTIONCODE": "1423",
            "DivisionName": "Division 14 (KAPRA N UPPAL)",
            "TestedDate": "29-08-2023",
            "TotalNumberOfLineMans": 11,
            "TotalSupplyCycles": 83,
            "TotalCans": 130,
            "NumberofLinemanUsingNaanythaApp": 3,
            "NumberofCyclesCovered": 6,
            "NumberofCANsTested": 8
        },
        {
            "DivisionCode": "14",
            "SectionName": "SAIBABA NAGAR",
            "SECTIONCODE": "1413",
            "DivisionName": "Division 14 (KAPRA N UPPAL)",
            "TestedDate": "29-08-2023",
            "TotalNumberOfLineMans": 5,
            "TotalSupplyCycles": 40,
            "TotalCans": 36,
            "NumberofLinemanUsingNaanythaApp": 3,
            "NumberofCyclesCovered": 9,
            "NumberofCANsTested": 6
        },
        {
            "DivisionCode": "14",
            "SectionName": "UPPAL",
            "SECTIONCODE": "1422",
            "DivisionName": "Division 14 (KAPRA N UPPAL)",
            "TestedDate": "29-08-2023",
            "TotalNumberOfLineMans": 13,
            "TotalSupplyCycles": 29,
            "TotalCans": 166,
            "NumberofLinemanUsingNaanythaApp": 3,
            "NumberofCyclesCovered": 3,
            "NumberofCANsTested": 11
        },
        {
            "DivisionCode": "15",
            "SectionName": "CHANDA NAGAR",
            "SECTIONCODE": "1511",
            "DivisionName": "Division 15 (RAMACHANDRAPURAM, PATANCHERVU N SERILINGAMPALLY)",
            "TestedDate": "29-08-2023",
            "TotalNumberOfLineMans": 10,
            "TotalSupplyCycles": 38,
            "TotalCans": 34,
            "NumberofLinemanUsingNaanythaApp": 6,
            "NumberofCyclesCovered": 21,
            "NumberofCANsTested": 17
        },
        {
            "DivisionCode": "15",
            "SectionName": "DEEPTHISRI NAGAR (DIV 15)",
            "SECTIONCODE": "1522",
            "DivisionName": "Division 15 (RAMACHANDRAPURAM, PATANCHERVU N SERILINGAMPALLY)",
            "TestedDate": "29-08-2023",
            "TotalNumberOfLineMans": 8,
            "TotalSupplyCycles": 10,
            "TotalCans": 26,
            "NumberofLinemanUsingNaanythaApp": 1,
            "NumberofCyclesCovered": 1,
            "NumberofCANsTested": 4
        },
        {
            "DivisionCode": "15",
            "SectionName": "Doyens section",
            "SECTIONCODE": "1542",
            "DivisionName": "Division 15 (RAMACHANDRAPURAM, PATANCHERVU N SERILINGAMPALLY)",
            "TestedDate": "",
            "TotalNumberOfLineMans": 3,
            "TotalSupplyCycles": 6,
            "TotalCans": 19,
            "NumberofLinemanUsingNaanythaApp": 0,
            "NumberofCyclesCovered": 0,
            "NumberofCANsTested": 0
        },
        {
            "DivisionCode": "15",
            "SectionName": "GACHIBOWLI (DIV 15)",
            "SECTIONCODE": "1513",
            "DivisionName": "Division 15 (RAMACHANDRAPURAM, PATANCHERVU N SERILINGAMPALLY)",
            "TestedDate": "29-08-2023",
            "TotalNumberOfLineMans": 8,
            "TotalSupplyCycles": 32,
            "TotalCans": 54,
            "NumberofLinemanUsingNaanythaApp": 3,
            "NumberofCyclesCovered": 5,
            "NumberofCANsTested": 11
        },
        {
            "DivisionCode": "15",
            "SectionName": "HAFEEZPET (DIV 15)",
            "SECTIONCODE": "1521",
            "DivisionName": "Division 15 (RAMACHANDRAPURAM, PATANCHERVU N SERILINGAMPALLY)",
            "TestedDate": "29-08-2023",
            "TotalNumberOfLineMans": 10,
            "TotalSupplyCycles": 23,
            "TotalCans": 55,
            "NumberofLinemanUsingNaanythaApp": 1,
            "NumberofCyclesCovered": 2,
            "NumberofCANsTested": 3
        },
        {
            "DivisionCode": "15",
            "SectionName": "KONDAPUR (DIV 15)",
            "SECTIONCODE": "1535",
            "DivisionName": "Division 15 (RAMACHANDRAPURAM, PATANCHERVU N SERILINGAMPALLY)",
            "TestedDate": "29-08-2023",
            "TotalNumberOfLineMans": 9,
            "TotalSupplyCycles": 58,
            "TotalCans": 164,
            "NumberofLinemanUsingNaanythaApp": 3,
            "NumberofCyclesCovered": 4,
            "NumberofCANsTested": 8
        },
        {
            "DivisionCode": "15",
            "SectionName": "MADHAPUR",
            "SECTIONCODE": "0614",
            "DivisionName": "Division 15 (RAMACHANDRAPURAM, PATANCHERVU N SERILINGAMPALLY)",
            "TestedDate": "29-08-2023",
            "TotalNumberOfLineMans": 12,
            "TotalSupplyCycles": 103,
            "TotalCans": 324,
            "NumberofLinemanUsingNaanythaApp": 1,
            "NumberofCyclesCovered": 10,
            "NumberofCANsTested": 37
        },
        {
            "DivisionCode": "15",
            "SectionName": "MIYAPUR",
            "SECTIONCODE": "0932",
            "DivisionName": "Division 15 (RAMACHANDRAPURAM, PATANCHERVU N SERILINGAMPALLY)",
            "TestedDate": "29-08-2023",
            "TotalNumberOfLineMans": 9,
            "TotalSupplyCycles": 23,
            "TotalCans": 34,
            "NumberofLinemanUsingNaanythaApp": 3,
            "NumberofCyclesCovered": 5,
            "NumberofCANsTested": 7
        },
        {
            "DivisionCode": "15",
            "SectionName": "NALLAGANDLA (DIV 15)",
            "SECTIONCODE": "1534",
            "DivisionName": "Division 15 (RAMACHANDRAPURAM, PATANCHERVU N SERILINGAMPALLY)",
            "TestedDate": "29-08-2023",
            "TotalNumberOfLineMans": 8,
            "TotalSupplyCycles": 56,
            "TotalCans": 101,
            "NumberofLinemanUsingNaanythaApp": 1,
            "NumberofCyclesCovered": 6,
            "NumberofCANsTested": 6
        },
        {
            "DivisionCode": "15",
            "SectionName": "PATANCHERU (DIV15)",
            "SECTIONCODE": "1533",
            "DivisionName": "Division 15 (RAMACHANDRAPURAM, PATANCHERVU N SERILINGAMPALLY)",
            "TestedDate": "29-08-2023",
            "TotalNumberOfLineMans": 12,
            "TotalSupplyCycles": 50,
            "TotalCans": 127,
            "NumberofLinemanUsingNaanythaApp": 5,
            "NumberofCyclesCovered": 14,
            "NumberofCANsTested": 31
        },
        {
            "DivisionCode": "15",
            "SectionName": "RAMACHANDRAPURAM",
            "SECTIONCODE": "1512",
            "DivisionName": "Division 15 (RAMACHANDRAPURAM, PATANCHERVU N SERILINGAMPALLY)",
            "TestedDate": "29-08-2023",
            "TotalNumberOfLineMans": 8,
            "TotalSupplyCycles": 26,
            "TotalCans": 181,
            "NumberofLinemanUsingNaanythaApp": 5,
            "NumberofCyclesCovered": 12,
            "NumberofCANsTested": 61
        },
        {
            "DivisionCode": "16",
            "SectionName": "ATTAPUR",
            "SECTIONCODE": "1613",
            "DivisionName": "Division 16  (RAJENDRANAGAR)",
            "TestedDate": "29-08-2023",
            "TotalNumberOfLineMans": 9,
            "TotalSupplyCycles": 43,
            "TotalCans": 138,
            "NumberofLinemanUsingNaanythaApp": 4,
            "NumberofCyclesCovered": 15,
            "NumberofCANsTested": 26
        },
        {
            "DivisionCode": "16",
            "SectionName": "BUDVEL (DIV16)",
            "SECTIONCODE": "1612",
            "DivisionName": "Division 16  (RAJENDRANAGAR)",
            "TestedDate": "29-08-2023",
            "TotalNumberOfLineMans": 7,
            "TotalSupplyCycles": 33,
            "TotalCans": 463,
            "NumberofLinemanUsingNaanythaApp": 3,
            "NumberofCyclesCovered": 7,
            "NumberofCANsTested": 40
        },
        {
            "DivisionCode": "16",
            "SectionName": "HYDERGUDA",
            "SECTIONCODE": "1611",
            "DivisionName": "Division 16  (RAJENDRANAGAR)",
            "TestedDate": "29-08-2023",
            "TotalNumberOfLineMans": 5,
            "TotalSupplyCycles": 35,
            "TotalCans": 121,
            "NumberofLinemanUsingNaanythaApp": 1,
            "NumberofCyclesCovered": 8,
            "NumberofCANsTested": 26
        },
        {
            "DivisionCode": "16",
            "SectionName": "KATEDAN",
            "SECTIONCODE": "1622",
            "DivisionName": "Division 16  (RAJENDRANAGAR)",
            "TestedDate": "29-08-2023",
            "TotalNumberOfLineMans": 12,
            "TotalSupplyCycles": 59,
            "TotalCans": 245,
            "NumberofLinemanUsingNaanythaApp": 1,
            "NumberofCyclesCovered": 5,
            "NumberofCANsTested": 8
        },
        {
            "DivisionCode": "16",
            "SectionName": "MAILERDEV PALLY",
            "SECTIONCODE": "1621",
            "DivisionName": "Division 16  (RAJENDRANAGAR)",
            "TestedDate": "29-08-2023",
            "TotalNumberOfLineMans": 8,
            "TotalSupplyCycles": 27,
            "TotalCans": 140,
            "NumberofLinemanUsingNaanythaApp": 4,
            "NumberofCyclesCovered": 11,
            "NumberofCANsTested": 50
        },
        {
            "DivisionCode": "16",
            "SectionName": "SULEMAN NAGAR",
            "SECTIONCODE": "1614",
            "DivisionName": "Division 16  (RAJENDRANAGAR)",
            "TestedDate": "29-08-2023",
            "TotalNumberOfLineMans": 11,
            "TotalSupplyCycles": 68,
            "TotalCans": 242,
            "NumberofLinemanUsingNaanythaApp": 1,
            "NumberofCyclesCovered": 3,
            "NumberofCANsTested": 10
        },
        {
            "DivisionCode": "33",
            "SectionName": "ALIABAD",
            "SECTIONCODE": "0252",
            "DivisionName": "Division 2 (b) (ASMANGADH)",
            "TestedDate": "29-08-2023",
            "TotalNumberOfLineMans": 5,
            "TotalSupplyCycles": 31,
            "TotalCans": 125,
            "NumberofLinemanUsingNaanythaApp": 2,
            "NumberofCyclesCovered": 3,
            "NumberofCANsTested": 6
        },
        {
            "DivisionCode": "33",
            "SectionName": "BALAPUR",
            "SECTIONCODE": "0235",
            "DivisionName": "Division 2 (b) (ASMANGADH)",
            "TestedDate": "29-08-2023",
            "TotalNumberOfLineMans": 6,
            "TotalSupplyCycles": 14,
            "TotalCans": 55,
            "NumberofLinemanUsingNaanythaApp": 1,
            "NumberofCyclesCovered": 1,
            "NumberofCANsTested": 3
        },
        {
            "DivisionCode": "33",
            "SectionName": "BANDLAGUDA  (DIV 2 (b))",
            "SECTIONCODE": "0256",
            "DivisionName": "Division 2 (b) (ASMANGADH)",
            "TestedDate": "",
            "TotalNumberOfLineMans": 4,
            "TotalSupplyCycles": 26,
            "TotalCans": 47,
            "NumberofLinemanUsingNaanythaApp": 0,
            "NumberofCyclesCovered": 0,
            "NumberofCANsTested": 0
        },
        {
            "DivisionCode": "33",
            "SectionName": "GOWLIPURA",
            "SECTIONCODE": "0253",
            "DivisionName": "Division 2 (b) (ASMANGADH)",
            "TestedDate": "29-08-2023",
            "TotalNumberOfLineMans": 4,
            "TotalSupplyCycles": 25,
            "TotalCans": 71,
            "NumberofLinemanUsingNaanythaApp": 1,
            "NumberofCyclesCovered": 5,
            "NumberofCANsTested": 20
        },
        {
            "DivisionCode": "33",
            "SectionName": "JAHANUMA",
            "SECTIONCODE": "0254",
            "DivisionName": "Division 2 (b) (ASMANGADH)",
            "TestedDate": "",
            "TotalNumberOfLineMans": 6,
            "TotalSupplyCycles": 20,
            "TotalCans": 46,
            "NumberofLinemanUsingNaanythaApp": 0,
            "NumberofCyclesCovered": 0,
            "NumberofCANsTested": 0
        },
        {
            "DivisionCode": "33",
            "SectionName": "JANGAMMET",
            "SECTIONCODE": "3311",
            "DivisionName": "Division 2 (b) (ASMANGADH)",
            "TestedDate": "",
            "TotalNumberOfLineMans": 2,
            "TotalSupplyCycles": 13,
            "TotalCans": 33,
            "NumberofLinemanUsingNaanythaApp": 0,
            "NumberofCyclesCovered": 0,
            "NumberofCANsTested": 0
        },
        {
            "DivisionCode": "33",
            "SectionName": "KANCHANBAGH",
            "SECTIONCODE": "3331",
            "DivisionName": "Division 2 (b) (ASMANGADH)",
            "TestedDate": "",
            "TotalNumberOfLineMans": 3,
            "TotalSupplyCycles": 11,
            "TotalCans": 10,
            "NumberofLinemanUsingNaanythaApp": 0,
            "NumberofCyclesCovered": 0,
            "NumberofCANsTested": 0
        },
        {
            "DivisionCode": "33",
            "SectionName": "MYSARAM",
            "SECTIONCODE": "0251",
            "DivisionName": "Division 2 (b) (ASMANGADH)",
            "TestedDate": "",
            "TotalNumberOfLineMans": 4,
            "TotalSupplyCycles": 21,
            "TotalCans": 44,
            "NumberofLinemanUsingNaanythaApp": 0,
            "NumberofCyclesCovered": 0,
            "NumberofCANsTested": 0
        },
        {
            "DivisionCode": "33",
            "SectionName": "RIYASATH NAGAR",
            "SECTIONCODE": "3321",
            "DivisionName": "Division 2 (b) (ASMANGADH)",
            "TestedDate": "29-08-2023",
            "TotalNumberOfLineMans": 5,
            "TotalSupplyCycles": 24,
            "TotalCans": 57,
            "NumberofLinemanUsingNaanythaApp": 2,
            "NumberofCyclesCovered": 3,
            "NumberofCANsTested": 5
        },
        {
            "DivisionCode": "34",
            "SectionName": "AUTONAGAR",
            "SECTIONCODE": "0243",
            "DivisionName": "Division 10 (b) (L.B.NAGAR)",
            "TestedDate": "29-08-2023",
            "TotalNumberOfLineMans": 6,
            "TotalSupplyCycles": 58,
            "TotalCans": 161,
            "NumberofLinemanUsingNaanythaApp": 1,
            "NumberofCyclesCovered": 5,
            "NumberofCANsTested": 16
        },
        {
            "DivisionCode": "34",
            "SectionName": "B.N.REDDY NAGAR",
            "SECTIONCODE": "1053",
            "DivisionName": "Division 10 (b) (L.B.NAGAR)",
            "TestedDate": "29-08-2023",
            "TotalNumberOfLineMans": 6,
            "TotalSupplyCycles": 14,
            "TotalCans": 59,
            "NumberofLinemanUsingNaanythaApp": 2,
            "NumberofCyclesCovered": 2,
            "NumberofCANsTested": 8
        },
        {
            "DivisionCode": "34",
            "SectionName": "KAMALANAGAR",
            "SECTIONCODE": "3461",
            "DivisionName": "Division 10 (b) (L.B.NAGAR)",
            "TestedDate": "",
            "TotalNumberOfLineMans": 5,
            "TotalSupplyCycles": 16,
            "TotalCans": 60,
            "NumberofLinemanUsingNaanythaApp": 0,
            "NumberofCyclesCovered": 0,
            "NumberofCANsTested": 0
        },
        {
            "DivisionCode": "34",
            "SectionName": "L.B.NAGAR",
            "SECTIONCODE": "0261",
            "DivisionName": "Division 10 (b) (L.B.NAGAR)",
            "TestedDate": "29-08-2023",
            "TotalNumberOfLineMans": 3,
            "TotalSupplyCycles": 20,
            "TotalCans": 70,
            "NumberofLinemanUsingNaanythaApp": 2,
            "NumberofCyclesCovered": 4,
            "NumberofCANsTested": 6
        },
        {
            "DivisionCode": "34",
            "SectionName": "MANSOORABAD",
            "SECTIONCODE": "1042",
            "DivisionName": "Division 10 (b) (L.B.NAGAR)",
            "TestedDate": "",
            "TotalNumberOfLineMans": 3,
            "TotalSupplyCycles": 18,
            "TotalCans": 66,
            "NumberofLinemanUsingNaanythaApp": 0,
            "NumberofCyclesCovered": 0,
            "NumberofCANsTested": 0
        },
        {
            "DivisionCode": "34",
            "SectionName": "NAGOLE",
            "SECTIONCODE": "1043",
            "DivisionName": "Division 10 (b) (L.B.NAGAR)",
            "TestedDate": "",
            "TotalNumberOfLineMans": 3,
            "TotalSupplyCycles": 20,
            "TotalCans": 61,
            "NumberofLinemanUsingNaanythaApp": 0,
            "NumberofCyclesCovered": 0,
            "NumberofCANsTested": 0
        },
        {
            "DivisionCode": "34",
            "SectionName": "NGO COLONY",
            "SECTIONCODE": "1052",
            "DivisionName": "Division 10 (b) (L.B.NAGAR)",
            "TestedDate": "29-08-2023",
            "TotalNumberOfLineMans": 5,
            "TotalSupplyCycles": 15,
            "TotalCans": 59,
            "NumberofLinemanUsingNaanythaApp": 3,
            "NumberofCyclesCovered": 6,
            "NumberofCANsTested": 22
        },
        {
            "DivisionCode": "34",
            "SectionName": "VANASTHALIPURAM (DIV 10)",
            "SECTIONCODE": "1041",
            "DivisionName": "Division 10 (b) (L.B.NAGAR)",
            "TestedDate": "",
            "TotalNumberOfLineMans": 7,
            "TotalSupplyCycles": 29,
            "TotalCans": 85,
            "NumberofLinemanUsingNaanythaApp": 0,
            "NumberofCyclesCovered": 0,
            "NumberofCANsTested": 0
        },
        {
            "DivisionCode": "6455",
            "SectionName": "Nagole STP (172 MLD)",
            "SECTIONCODE": "6417",
            "DivisionName": "STP DIVISION 2",
            "TestedDate": "",
            "TotalNumberOfLineMans": 1,
            "TotalSupplyCycles": 3,
            "TotalCans": 9,
            "NumberofLinemanUsingNaanythaApp": 0,
            "NumberofCyclesCovered": 0,
            "NumberofCANsTested": 0
        }
    ]
}